grambot/__init__.py
grambot/apiClient.py
grambot/cache.py
grambot/exception.py
grambot/filters.py
grambot/gramClient.py
grambot/py.typed
grambot/session.py
grambot/handlers/__init__.py
grambot/handlers/callbackQueryHandler.py
grambot/handlers/handler.py
grambot/handlers/inlineQueryHandler.py
grambot/handlers/messageHandler.py
grambot/method/__init__.py
grambot/method/chats/__init__.py
grambot/method/chats/getChat.py
grambot/method/chats/getChatAdministrators.py
grambot/method/decorators/__init__.py
grambot/method/decorators/onCallbackQuery.py
grambot/method/decorators/onInlineQuery.py
grambot/method/decorators/onMessage.py
grambot/method/messages/__init__.py
grambot/method/messages/forwardMessage.py
grambot/method/messages/sendMessage.py
grambot/method/user/__init__.py
grambot/method/user/getMe.py
grambot/method/user/getUser.py
grambot/method/user/getUserProfilePhotos.py
grambot/method/utils/__init__.py
grambot/method/utils/start.py
grambot/method/utils/webhook.py
grambot/types/__init__.py
grambot/types/callbackQuery.py
grambot/types/inlineQuery.py
grambot/types/update.py
grambot/types/business/__init__.py
grambot/types/business/businessConnection.py
grambot/types/business/businessDeleteMessage.py
grambot/types/chats/__init__.py
grambot/types/chats/chatFullInfo.py
grambot/types/chats/chatMember/__init__.py
grambot/types/chats/chatMember/chatMemberAdministrator.py
grambot/types/chats/chatMember/chatMemberBanned.py
grambot/types/chats/chatMember/chatMemberLeft.py
grambot/types/chats/chatMember/chatMemberOwner.py
grambot/types/chats/chatMember/chatMemberRestricted.py
grambot/types/chats/chatMember/chatMembersMember.py
grambot/types/keyboard/__init__.py
grambot/types/keyboard/replyKeyboardMarkup.py
grambot/types/messages/__init__.py
grambot/types/messages/message.py
grambot/types/users/__init__.py
grambot/types/users/user.py
grambot/types/users/userProfilePhotos.py
grambot-1.0.2.dist-info/LICENSE
grambot-1.0.2.dist-info/METADATA
grambot-1.0.2.dist-info/WHEEL
grambot-1.0.2.dist-info/top_level.txt
grambot-1.0.2.dist-info/RECORD
