Metadata-Version: 2.1
Name: grambot
Version: 1.0.2
Summary: Grambot Based Library For Your Telegram Bot.
Home-page: https://github.com/AyiinXd/grambot
Author: AyiinXd
Author-email: ayingaming98@gmail.com
License: GNU Lesser General Public License v3.0 (LGPL-3.0)
Project-URL: Bug Tracker, https://github.com/AyiinXd/grambot/issues
Project-URL: Source Code, https://github.com/AyiinXd/grambot
Classifier: Programming Language :: Python :: 3
Classifier: Programming Language :: Python :: 3.8
Classifier: Programming Language :: Python :: 3.9
Classifier: Programming Language :: Python :: 3.10
Classifier: Programming Language :: Python :: 3.11
Classifier: Programming Language :: Python :: 3.12
Classifier: License :: OSI Approved :: GNU General Public License v3 (GPLv3)
Classifier: Operating System :: OS Independent
Requires-Python: ~=3.7
License-File: LICENSE
Requires-Dist: asyncio
Requires-Dist: requests
